extract.py
run_table_app.py
table_app.py
tabled/assignment.py
tabled/extract.py
tabled/fileinput.py
tabled/formats/__init__.py
tabled/formats/common.py
tabled/formats/csv.py
tabled/formats/html.py
tabled/formats/markdown.py
tabled/heuristics/__init__.py
tabled/heuristics/cells.py
tabled/inference/detection.py
tabled/inference/models.py
tabled/inference/recognition.py
tabled/schema.py
tabled/settings.py
tabled_pdf-0.2.0.dist-info/LICENSE
tabled_pdf-0.2.0.dist-info/METADATA
tabled_pdf-0.2.0.dist-info/WHEEL
tabled_pdf-0.2.0.dist-info/entry_points.txt
tabled_pdf-0.2.0.dist-info/RECORD
