Metadata-Version: 2.1
Name: tabled-pdf
Version: 0.2.0
Summary: Detect and recognize tables in PDFs and images.
Home-page: https://github.com/VikParuchuri/tabled
License: GPL-3.0-or-later
Keywords: table,table-recognition,ocr,pdf
Author: Vik Paruchuri
Author-email: github@vikas.sh
Requires-Python: >=3.10,<4.0
Classifier: License :: OSI Approved :: GNU General Public License v3 or later (GPLv3+)
Classifier: Programming Language :: Python :: 3
Classifier: Programming Language :: Python :: 3.10
Classifier: Programming Language :: Python :: 3.11
Classifier: Programming Language :: Python :: 3.12
Classifier: Programming Language :: Python :: 3.13
Requires-Dist: click (>=8.1.7,<9.0.0)
Requires-Dist: pydantic (>=2.9.2,<3.0.0)
Requires-Dist: pydantic-settings (>=2.5.2,<3.0.0)
Requires-Dist: pypdfium2 (>=4.30.0,<5.0.0)
Requires-Dist: python-dotenv (>=1.0.1,<2.0.0)
Requires-Dist: scikit-learn (>=1.5.2,<2.0.0)
Requires-Dist: surya-ocr (>=0.8.0,<0.9.0)
Requires-Dist: tabulate (>=0.9.0,<0.10.0)
Project-URL: Repository, https://github.com/VikParuchuri/tabled
